MANIFEST.in
setup.py
scripts/hpcnotebook
scripts/sparkcluster
sparkhpc/__init__.py
sparkhpc/lsfsparkjob.py
sparkhpc/slurmsparkjob.py
sparkhpc/sparkjob.py
sparkhpc.egg-info/PKG-INFO
sparkhpc.egg-info/SOURCES.txt
sparkhpc.egg-info/dependency_links.txt
sparkhpc.egg-info/requires.txt
sparkhpc.egg-info/top_level.txt
sparkhpc/templates/sparkjob.lsf.template
sparkhpc/templates/sparkjob.slurm.template