Metadata-Version: 1.0
Name: sparkhpc
Version: 0.3
Summary: spark deployment on hpc resources made easy
Home-page: http://sparkhpc.readthedocs.io
Author: Rok Roskar
Author-email: roskar@ethz.ch
License: UNKNOWN
Keywords: pyspark,spark,hpc,slurm,lsf
Platform: UNKNOWN
